Workbook

Sheet Inputs
A1: Input | B1: Value | C1: Unit | D1: Source
A2: Electrolyser capacity | B2: 5 | C2: MW | D2: Feasibility study
A3: Full-load hours | B3: 5200 | C3: h/a | D3: Dispatch model
A4: Specific consumption (system) | B4: 54 | C4: kWh/kg | D4: Vendor RFI, average of PEM bids
A5: Electricity price incl. network charges | B5: 62 | C5: EUR/MWh | D5: Sleeved Harrow Bay + grid
A6: WACC (nominal, pre-tax) | B6: 0.07 | D6: Finance guidance 2026
A7: Lifetime | B7: 20 | C7: years
A8: Total capex | B8: =Capex!B10 | C8: EUR m | D8: Capex tab
A9: Fixed O&M | B9: 0.025 | C9: of capex p.a.
A10: Stack replacement provision | B10: 0.22 | C10: EUR m/a | D10: Replacement at ~70,000 h
A11: Staff (2 FTE shared) | B11: 0.25 | C11: EUR m/a
A12: Water and consumables | B12: 0.03 | C12: EUR m/a
A13: Innovation Fund grant | B13: 10.5 | C13: EUR m | D13: Scenario – set to 0 for no-grant case

Sheet Capex
A1: Item | B1: EUR m
A2: Electrolyser stacks and power electronics | B2: 7.4
A3: Balance of plant (water treatment, cooling, purification) | B3: 3.1
A4: Compression (30 → 200 bar) and buffer storage 2.5 t | B4: 2.3
A5: Hydrogen pipeline to Arcturus rolling mill (1.4 km) | B5: 1.3
A6: Grid connection 33 kV and transformer | B6: 1.6
A7: Civil works and electrolyser hall | B7: 2.2
A8: Engineering, project management, owner's costs | B8: 1.9
A9: Contingency (≈ 9 %) | B9: 1.7
A10: Total | B10: =SUM(B2:B9)

Sheet Calculation
A1: Calculation | B1: No grant | C1: With grant | D1: Unit
A2: Electricity consumed | B2: =Inputs!B2*Inputs!B3 | C2: =Inputs!B2*Inputs!B3 | D2: MWh/a
A3: Hydrogen produced | B3: =B2*1000/Inputs!B4 | C3: =C2*1000/Inputs!B4 | D3: kg/a
A4: Capital recovery factor | B4: =Inputs!B6/(1-(1+Inputs!B6)^-Inputs!B7) | C4: =B4
A5: Annualised capex | B5: =Inputs!B8*B4 | C5: =(Inputs!B8-Inputs!B13)*C4 | D5: EUR m/a
A6: Fixed opex | B6: =Inputs!B8*Inputs!B9+Inputs!B10+Inputs!B11+Inputs!B12 | C6: =B6 | D6: EUR m/a
A7: Electricity cost | B7: =B2*Inputs!B5/1000000 | C7: =C2*Inputs!B5/1000000 | D7: EUR m/a
A8: Total annual cost | B8: =B5+B6+B7 | C8: =C5+C6+C7 | D8: EUR m/a
A9: LCOH | B9: =B8*1000000/B3 | C9: =C8*1000000/C3 | D9: EUR/kg
A10: of which capex | B10: =B5*1000000/B3 | C10: =C5*1000000/C3 | D10: EUR/kg
A11: of which fixed opex | B11: =B6*1000000/B3 | C11: =C6*1000000/C3 | D11: EUR/kg
A12: of which electricity | B12: =B7*1000000/B3 | C12: =C7*1000000/C3 | D12: EUR/kg

Sheet Sensitivities
A1: Sensitivity | B1: Favourable (EUR/kg) | C1: Unfavourable (EUR/kg) | D1: Swing
A2: Electricity price 42 / 82 EUR/MWh | B2: 8.64 | C2: 10.8 | D2: =C2-B2
A3: Full-load hours 6,500 / 4,000 | B3: 8.44 | C3: 11.63 | D3: =C3-B3
A4: Capex −20 % / +20 % | B4: 8.65 | C4: 10.78 | D4: =C4-B4
A5: WACC 5 % / 9 % | B5: 9.09 | C5: 10.39 | D5: =C5-B5
A6: Specific consumption 51 / 58 kWh/kg | B6: 9.18 | C6: 10.44 | D6: =C6-B6

Sheet Price x hours
A1: LCOH (EUR/kg, no grant) by electricity price and full-load hours
A3: Electricity price (EUR/MWh) \ Full-load hours | B3: 3500 | C3: 4000 | D3: 4500 | E3: 5200 | F3: 6000 | G3: 6500
A4: 40 | B4: 11.62 | C4: 10.44 | D4: 9.52 | E4: 8.53 | F4: 7.68 | G4: 7.26
A5: 50 | B5: 12.16 | C5: 10.98 | D5: 10.06 | E5: 9.07 | F5: 8.22 | G5: 7.8
A6: 62 | B6: 12.81 | C6: 11.63 | D6: 10.71 | E6: 9.72 | F6: 8.87 | G6: 8.44
A7: 70 | B7: 13.24 | C7: 12.06 | D7: 11.14 | E7: 10.15 | F7: 9.3 | G7: 8.88
A8: 80 | B8: 13.78 | C8: 12.6 | D8: 11.68 | E8: 10.69 | F8: 9.84 | G8: 9.42
A9: 90 | B9: 14.32 | C9: 13.14 | D9: 12.22 | E9: 11.23 | F9: 10.38 | G9: 9.96
