Workbook

Sheet Assumptions
A1: Assumption | B1: Value | C1: Unit | D1: Comment
A2: Power | B2: 100 | C2: MW | D2: Grid application July 2026
A3: Energy | B3: 200 | C3: MWh | D3: 2-hour duration
A4: Round-trip efficiency | B4: 0.86 | D4: At point of connection, BoL
A5: Cycles per year | B5: 365 | C5: cycles | D5: Warranty limit 1.2 cycles/day
A6: Capex | B6: 64 | C6: EUR m | D6: Incl. grid, excl. development
A7: Opex | B7: 11.5 | C7: EUR k/MW/a | D7: O&M, insurance, rent, optimiser fee
A8: Optimiser fee | B8: 0.07 | C8: of trading revenue | D8: Indicative from two optimisers
A9: Capacity market de-rating (2h) | B9: 0.21 | D9: Applied to connection capacity
A10: Clearing price capacity market | B10: 76 | C10: EUR k/MW(derated)/a | D10: Recent auctions, held flat real
A11: COD | B11: 2029-09-30 | D11: Subject to grid offer

Sheet Stack
A1: Revenue stream (EUR k/MW/a) | B1: 2029 | C1: 2030 | D1: 2031 | E1: 2032 | F1: 2033 | G1: 2034 | H1: 2035 | I1: 2036 | J1: 2037 | K1: 2038 | L1: 2039 | M1: 2040 | N1: 2041 | O1: 2042 | P1: 2043
A2: Frequency response (DC/DM/DR) | B2: 62 | C2: 52 | D2: 44 | E2: 38 | F2: 34 | G2: 31 | H2: 29 | I2: 27 | J2: 26 | K2: 25 | L2: 24 | M2: 23 | N2: 22 | O2: 22 | P2: 21
A3: Wholesale arbitrage | B3: 38 | C3: 44 | D3: 49 | E3: 53 | F3: 56 | G3: 58 | H3: 60 | I3: 61 | J3: 62 | K3: 62 | L3: 63 | M3: 63 | N3: 63 | O3: 63 | P3: 63
A4: Balancing Mechanism | B4: 21 | C4: 23 | D4: 24 | E4: 25 | F4: 25 | G4: 25 | H4: 24 | I4: 24 | J4: 23 | K4: 23 | L4: 22 | M4: 22 | N4: 22 | O4: 21 | P4: 21
A5: Capacity market | B5: 16 | C5: 16 | D5: 16 | E5: 16 | F5: 16 | G5: 16 | H5: 16 | I5: 16 | J5: 16 | K5: 16 | L5: 16 | M5: 16 | N5: 16 | O5: 16 | P5: 16
A6: Stability / reactive services | B6: 4 | C6: 5 | D6: 6 | E6: 6 | F6: 6 | G6: 6 | H6: 6 | I6: 6 | J6: 6 | K6: 6 | L6: 6 | M6: 6 | N6: 6 | O6: 6 | P6: 6
A7: Total | B7: =SUM(B2:B6) | C7: =SUM(C2:C6) | D7: =SUM(D2:D6) | E7: =SUM(E2:E6) | F7: =SUM(F2:F6) | G7: =SUM(G2:G6) | H7: =SUM(H2:H6) | I7: =SUM(I2:I6) | ... P7: =SUM(P2:P6)

Sheet Cash flow
A1: Year | B1: Revenue (EUR m) | C1: Opex (EUR m) | D1: EBITDA (EUR m) | E1: Degradation factor
A2: 2029 | B2: =Stack!B7*100/1000 | C2: =Assumptions!B7*100/1000*(1.025^(2029-2029)) | D2: =B2-C2 | E2: 1
A3: 2030 | B3: =Stack!C7*100/1000 | C3: =Assumptions!B7*100/1000*(1.025^(2030-2029)) | D3: =B3-C3 | E3: 0.98
A4: 2031 | B4: =Stack!D7*100/1000 | C4: =Assumptions!B7*100/1000*(1.025^(2031-2029)) | D4: =B4-C4 | E4: 0.96
A5: 2032 | B5: =Stack!E7*100/1000 | C5: =Assumptions!B7*100/1000*(1.025^(2032-2029)) | D5: =B5-C5 | E5: 0.941
A6: 2033 | B6: =Stack!F7*100/1000 | C6: =Assumptions!B7*100/1000*(1.025^(2033-2029)) | D6: =B6-C6 | E6: 0.922
A7: 2034 | B7: =Stack!G7*100/1000 | C7: =Assumptions!B7*100/1000*(1.025^(2034-2029)) | D7: =B7-C7 | E7: 0.904
A8: 2035 | B8: =Stack!H7*100/1000 | C8: =Assumptions!B7*100/1000*(1.025^(2035-2029)) | D8: =B8-C8 | E8: 0.886
A9: 2036 | B9: =Stack!I7*100/1000 | C9: =Assumptions!B7*100/1000*(1.025^(2036-2029)) | D9: =B9-C9 | E9: 0.868
A10: 2037 | B10: =Stack!J7*100/1000 | C10: =Assumptions!B7*100/1000*(1.025^(2037-2029)) | D10: =B10-C10 | E10: 0.851
A11: 2038 | B11: =Stack!K7*100/1000 | C11: =Assumptions!B7*100/1000*(1.025^(2038-2029)) | D11: =B11-C11 | E11: 0.834
A12: 2039 | B12: =Stack!L7*100/1000 | C12: =Assumptions!B7*100/1000*(1.025^(2039-2029)) | D12: =B12-C12 | E12: 0.817
A13: 2040 | B13: =Stack!M7*100/1000 | C13: =Assumptions!B7*100/1000*(1.025^(2040-2029)) | D13: =B13-C13 | E13: 0.801
A14: 2041 | B14: =Stack!N7*100/1000 | C14: =Assumptions!B7*100/1000*(1.025^(2041-2029)) | D14: =B14-C14 | E14: 0.785
A15: 2042 | B15: =Stack!O7*100/1000 | C15: =Assumptions!B7*100/1000*(1.025^(2042-2029)) | D15: =B15-C15 | E15: 0.769
A16: 2043 | B16: =Stack!P7*100/1000 | C16: =Assumptions!B7*100/1000*(1.025^(2043-2029)) | D16: =B16-C16 | E16: 0.754
A17: Total | B17: =SUM(B2:B16) | C17: =SUM(C2:C16) | D17: =SUM(D2:D16)

Sheet Scenarios
A1: Scenario | B1: Avg revenue first 10 years (EUR k/MW/a) | C1: Key drivers
A2: Low | B2: 106.5 | C2: Ancillary service saturation by 2030, low spreads, non-firm connection
A3: Base | B3: 136.5 | C3: Central market view (two independent forecasters, averaged)
A4: High | B4: 165.2 | C4: Higher gas price volatility, slower BESS build-out
